inventree_ptouch_endless/__init__.py
inventree_ptouch_endless/plugin.py
inventree_ptouch_endless/labelprinterkit/LICENSE
inventree_ptouch_endless/labelprinterkit/__init__.py
inventree_ptouch_endless/labelprinterkit/constants.py
inventree_ptouch_endless/labelprinterkit/job.py
inventree_ptouch_endless/labelprinterkit/label.py
inventree_ptouch_endless/labelprinterkit/page.py
inventree_ptouch_endless/labelprinterkit/printers.py
inventree_ptouch_endless/labelprinterkit/__pycache__/__init__.cpython-312.pyc
inventree_ptouch_endless/labelprinterkit/__pycache__/constants.cpython-312.pyc
inventree_ptouch_endless/labelprinterkit/__pycache__/job.cpython-312.pyc
inventree_ptouch_endless/labelprinterkit/__pycache__/page.cpython-312.pyc
inventree_ptouch_endless/labelprinterkit/__pycache__/printers.cpython-312.pyc
inventree_ptouch_endless/labelprinterkit/backends/__init__.py
inventree_ptouch_endless/labelprinterkit/backends/bluetooth.py
inventree_ptouch_endless/labelprinterkit/backends/network.py
inventree_ptouch_endless/labelprinterkit/backends/usb.py
inventree_ptouch_endless/labelprinterkit/backends/__pycache__/__init__.cpython-312.pyc
inventree_ptouch_endless/labelprinterkit/backends/__pycache__/network.cpython-312.pyc
inventree_ptouch_endless/templates/label/ptouch_base.html
inventree_ptouch_endless/templatetags/__init__.py
inventree_ptouch_endless/templatetags/ptouch.py
inventree_ptouch_endless/templatetags/__pycache__/__init__.cpython-312.pyc
inventree_ptouch_endless/templatetags/__pycache__/ptouch.cpython-312.pyc
inventree_ptouch_endless_plugin-0.1.0.dist-info/licenses/LICENSE
inventree_ptouch_endless_plugin-0.1.0.dist-info/METADATA
inventree_ptouch_endless_plugin-0.1.0.dist-info/WHEEL
inventree_ptouch_endless_plugin-0.1.0.dist-info/entry_points.txt
inventree_ptouch_endless_plugin-0.1.0.dist-info/top_level.txt
inventree_ptouch_endless_plugin-0.1.0.dist-info/RECORD
