Metadata-Version: 2.4
Name: inventree-ptouch-endless-plugin
Version: 0.1.0
Summary: Printer driver for brother ptouch series printers, supporting a variable length labels.
Home-page: https://github.com/mschaf/inventree-ptouch-endless-plugin
Author: Martin Schaflitzl
Author-email: dev@martin-sc.de
License: Apache License Version 2.0
Keywords: inventree label printer printing inventory dynamic width variable length ptouch
Classifier: Programming Language :: Python :: 3
Classifier: Operating System :: OS Independent
Classifier: Framework :: InvenTree
Requires-Python: >=3.9
License-File: LICENSE
Requires-Dist: pillow
Dynamic: author
Dynamic: author-email
Dynamic: classifier
Dynamic: description
Dynamic: description-content-type
Dynamic: home-page
Dynamic: keywords
Dynamic: license
Dynamic: license-file
Dynamic: requires-dist
Dynamic: requires-python
Dynamic: summary
